{
  "id": "beef-caldereta",
  "name": "Beef Caldereta",
  "description": "A rich and spicy beef stew with liver spread, olives, potatoes, and bell peppers in a tomato-based sauce. A fiesta staple and one of the most popular party dishes.",
  "type": [
    "main_dish"
  ],
  "main_ingredients": [
    "beef",
    "liver spread",
    "tomato sauce",
    "olives",
    "potatoes"
  ],
  "occasion": [
    "fiesta",
    "party",
    "birthday",
    "christmas"
  ],
  "flavor_profile": [
    "savory",
    "spicy",
    "sour"
  ],
  "cooking_method": [
    "stewed"
  ],
  "tags": [
    "beef",
    "spicy",
    "fiesta",
    "tomato"
  ],
  "image_url": "https://v3b.fal.media/files/b/0a99d4bc/-DDR6aye8eBreCY0vAqeY.jpg",
  "image_credit": "AI Generated (fal.ai Realistic Vision)"
}