{
  "id": "bringhe",
  "name": "Bringhe",
  "description": "A Kapampangan festive rice dish cooked in coconut milk and turmeric wrapped in banana leaves. Often called the Filipino paella and served at weddings and fiestas.",
  "type": [
    "rice_dish",
    "main_dish"
  ],
  "main_ingredients": [
    "glutinous rice",
    "coconut milk",
    "turmeric",
    "chicken"
  ],
  "occasion": [
    "fiesta",
    "wedding",
    "christmas",
    "party"
  ],
  "flavor_profile": [
    "savory",
    "sweet"
  ],
  "cooking_method": [
    "steamed"
  ],
  "origin_region": "Pampanga",
  "tags": [
    "kapampangan",
    "rice",
    "banana leaf",
    "turmeric"
  ],
  "image_url": "https://pub-2e1172f9672f425f9d4a549a832fbd21.r2.dev/dishes/bringhe.jpg",
  "image_credit": "AI Generated (fal.ai Realistic Vision) hosted on Cloudflare R2"
}