{
  "id": "lechon",
  "name": "Lechon",
  "description": "A whole roasted pig slow-cooked over charcoal until the skin is crispy and the meat is tender. The centerpiece of Filipino celebrations and considered one of the best roasted pigs in the world.",
  "type": [
    "main_dish"
  ],
  "main_ingredients": [
    "whole pig",
    "lemongrass",
    "garlic",
    "onion"
  ],
  "occasion": [
    "fiesta",
    "christmas",
    "birthday",
    "wedding",
    "party"
  ],
  "flavor_profile": [
    "savory",
    "umami"
  ],
  "cooking_method": [
    "roasted"
  ],
  "tags": [
    "whole pig",
    "crispy skin",
    "celebration",
    "cebu"
  ],
  "image_url": "https://image.pollinations.ai/prompt/Lechon%20Filipino%20food%20photography%20overhead%20shot%20natural%20lighting",
  "image_credit": "AI Generated (prototype - Pollinations.ai)"
}