{
  "id": "longganisa",
  "name": "Longganisa",
  "description": "Filipino cured sausage that varies by region — sweet Vigan longganisa, garlicky Lucban longganisa, and many more. A breakfast staple typically served with garlic rice and egg.",
  "type": [
    "breakfast",
    "main_dish"
  ],
  "main_ingredients": [
    "pork",
    "garlic",
    "vinegar",
    "sugar"
  ],
  "occasion": [
    "breakfast",
    "everyday"
  ],
  "flavor_profile": [
    "sweet",
    "savory",
    "salty"
  ],
  "cooking_method": [
    "fried"
  ],
  "tags": [
    "sausage",
    "breakfast",
    "silog",
    "regional"
  ],
  "image_url": "https://v3b.fal.media/files/b/0a99d4d4/ilSfs-fgso_0kaChB-cDw.jpg",
  "image_credit": "AI Generated (fal.ai Realistic Vision)"
}